vbgenpost/__init__.py
vbgenpost/__main__.py
vbgenpost/choice_option.py
vbgenpost/copyprompt.py
vbgenpost/functions.py
vbgenpost/geminivision.py
vbgenpost/gptloop.py
vbgenpost/gptvision.py
vbgenpost/main.py
vbgenpost/prompts.py
vbgenpost/solution.py
vbgenpost/token_cost_calculations.py
vbgenpost-0.1.0.dist-info/METADATA
vbgenpost-0.1.0.dist-info/WHEEL
vbgenpost-0.1.0.dist-info/entry_points.txt
vbgenpost-0.1.0.dist-info/RECORD
